{
    "name-of-spell": {
        "name": "Name of Spell",
        "level": 1,
        "school": "divination",

        "castTime": {
            "amount": 1,
            "time": "action",
            "ritual": true
        },
        "range": "60ft.",
        "vsm": [true, true, "material components"],
        "duration": {
            "amount": 1,
            "time": "hour",
            "concentration": true
        },
        
        "desc": [
            {
                "desc": "This spell does a thing."
            },
            {
                "desc": "Alternatively, you may have this spell do a different thing."
            },
            {
                "desc": "If you stop doing the thing, the spell ends early."
            }
        ],
        "levels": null,
        
        "lists": ["wizard"],
        "source": "Source"
    },
    "bane": {
        "name": "Bane",
        "level": 1,
        "school": "enchantment",

        "castTime": {
            "amount": 1,
            "time": "action"
        },
        "range": "30ft.",
        "vsm": [true, true, "a drop of blood"],
        "duration": {
            "amount": 1,
            "time": "minute",
            "concentration": true
        },
        
        "desc": [
            {
                "desc": "Up to {*} creatures of your choice that you can see within range must make CHA saving throws. Whenever a target that fails this saving throw makes an attack roll or a saving throw before the spell ends, the target must roll a d4 and subtract the number rolled from the attack roll or saving throw."
            }
        ],
        "levels": [3, 4, 5, 6, 7, 8, 9, 10],
        
        "lists": ["bard", "cleric"],
        "source": "Player's Handbook"
    },
    "chaos-bolt": {
        "name": "Chaos Bolt",
        "level": 1,
        "school": "evocation",

        "castTime": {
            "amount": 1,
            "time": "action"
        },
        "range": "120ft.",
        "vsm": [true, true, false],
        "duration": {
            "time": "instantaneous"
        },
        
        "desc": [
            {
                "desc": "You hurl an undulating, warbling mass of chaotic energy at one creature in range. Make a ranged spell attack against the target. On a hit, the target takes 2d8 + {*}d6 damage. Choose one of the d8s. The number rolled on that die determines the attack's damage type, as shown below.",
                "content": {
                    "header": true,
                    "content": [
                        ["d8", "Damage Type"],
                        [1, "@acid"],
                        [2, "@cold"],
                        [3, "@fire"],
                        [4, "@force"],
                        [5, "@lightning"],
                        [6, "@poison"],
                        [7, "@psychic"],
                        [8, "@thunder"]
                    ]
                }
            },
            {
                "desc": "If you roll the same number on both d8s, the chaotic energy leaps from the target to a different creature of your choice within 30 feet of it. Make a new attack roll against the new target, and make a new damage roll, which could cause the chaotic energy to leap again. However, a creature can be targeted only once by each casting of this spell."
            }
        ],
        "levels": [1, 2, 3, 4, 5, 6, 7, 8, 9],
        
        "lists": ["sorcerer"],
        "source": "Xanathar's Guide to Everything"
    },
    "frost-fingers": {
        "name": "Frost Fingers",
        "level": 1,
        "school": "evocation",

        "castTime": {
            "amount": 1,
            "time": "action"
        },
        "range": "self (15ft. cone)",
        "vsm": [true, true, false],
        "duration": {
            "time": "instantaneous"
        },
        
        "desc": [
            {
                "desc": "Freezing cold blasts from your fingertips in a 15ft. cone. Each creature in that area must make a CON saving throw, taking {*}d8 @cold damage on a failed save, or half as much damage on a successful one. The cold freezes nonmagical liquids in the area that aren't being worn or carried."
            }
        ],
        "levels": [2, 3, 4, 5, 6, 7, 8, 9, 10],
        
        "lists": ["wizard"],
        "source": "Icewind Dale - Rime of the Frostmaiden"
    },
    "hunters-mark": {
        "name": "Hunter's Mark",
        "level": 1,
        "school": "divination",

        "castTime": {
            "amount": 1,
            "time": "bonus action"
        },
        "range": "90ft.",
        "vsm": [true, false, false],
        "duration": {
            "time": "{*}"
        },
        
        "desc": [
            {
                "desc": "You choose a creature you can see within range and mystically mark it as your quarry. Until the spell ends, you deal an extra 1d6 damage to the target whenever you hit it with a weapon attack, and you have advantage on any Perception (Wisdom) or Survival (Wisdom) check you make to find it. If the target drops to 0 hit points before this spell ends, you may use a bonus action on a subsequent turn of yours to mark a new creature."
            }
        ],
        "levels": ["1 hour", "1 hour", "8 hours", "8 hours", "24 hours", "24 hours", "24 hours", "24 hours", "24 hours"],
        
        "lists": ["ranger"],
        "source": "Player's Handbook"
    },
    "identify": {
        "name": "Identify",
        "level": 1,
        "school": "divination",

        "castTime": {
            "amount": 1,
            "time": "minute",
            "ritual": true
        },
        "range": "touch",
        "vsm": [true, true, "a pearl worth at least 100 gp and an owl feather"],
        "duration": {
            "time": "instantaneous"
        },
        
        "desc": [
            {
                "desc": "You choose one object that you must touch throughout the casting of the spell. If it is a magic item or some other magic-imbued object, you learn its properties and how to use them, whether it requires attunement to use, and how many charges it has, if any. You learn whether any spells are affecting the item and what they are. If the item was created by a spell, you learn which spell created it. If you instead touch a creature throughout the casting, you learn what spells, if any, are currently affecting it."
            }
        ],
        "levels": null,
        
        "lists": ["artificer", "bard", "wizard"],
        "source": "Player's Handbook"
    },
    "inflict-wounds": {
        "name": "Inflict Wounds",
        "level": 1,
        "school": "necromancy",

        "castTime": {
            "amount": 1,
            "time": "action"
        },
        "range": "touch",
        "vsm": [true, true, false],
        "duration": {
            "time": "instantaneous"
        },
        
        "desc": [
            {
                "desc": "Make a melee spell attack against a creature you are able to reach. On a hit, the target takes {*}d10 necrotic damage."
            }
        ],
        "levels": [3, 4, 5, 6, 7, 8, 9, 10, 11],
        
        "lists": ["cleric"],
        "source": "Player's Handbook"
    },
    "shillelagh": {
        "name": "Shillelagh",
        "level": 0,
        "school": "transmutation",

        "castTime": {
            "amount": 1,
            "time": "bonus action"
        },
        "range": "touch",
        "vsm": [true, true, "mistletoe, a shamrock leaf, and a club or quarterstaff"],
        "duration": {
            "amount": 1,
            "time": "minute"
        },
        
        "desc": [
            {
                "desc": "The wood of a club or quarterstaff you are holding is imbued with nature's power. For the duration, you may use your spellcasting ability instead of STR for the attack and damage rolls of melee attacks using that weapon, and the weapon's damage die becomes a d8. The weapon also becomes magical, if it is not already. The spell ends if you cast it again or if you let go of the weapon."
            }
        ],
        "levels": null,
        
        "lists": ["druid"],
        "source": "Player's Handbook"
    },
    "primal-savagery": {
        "name": "Primal Savagery",
        "level": 0,
        "school": "transmutation",

        "castTime": {
            "amount": 1,
            "time": "action"
        },
        "range": "self",
        "vsm": [false, true, false],
        "duration": {
            "time": "instantaneous"
        },
        
        "desc": [
            {
                "desc": "You channel primal magic to cause your teeth or fingernails to sharpen, ready to deliver a corrosive attack. Make a melee spell attack against one creature within 5ft. of you. On a hit, the target takes {*}d10 @acid damage. After you make the attack, your teeth or fingernails return to normal."
            }
        ],
        "levels": [1, 2, 3, 4],
        
        "lists": ["druid"],
        "source": "Xanathar's Guide to Everything"
    },
    "ceremony": {
        "name": "Ceremony",
        "level": 1,
        "school": "abjuration",

        "castTime": {
            "amount": 1,
            "time": "hour",
            "ritual": true
        },
        "range": "touch",
        "vsm": [true, true, "25 gp worth of powdered silver, which the spell consumes"],
        "duration": {
            "time": "special"
        },
        
        "desc": [
            {
                "desc": "You perform one of several religious ceremonies. When you cast the spell, choose one of the following ceremonies, the target of which must be within 10ft. of you throughout the casting.",
                "type": "list",
                "content": [
                    {
                        "name": "Atonement",
                        "desc": "ou touch one willing creature whose alignment has changed, and you make a DC 20 Wisdom (Insight) check. On a successful check, you restore the target to its original alignment."
                    },
                    {
                        "name": "Bless Water",
                        "desc": "You touch one vial of water and cause it to become holy water."
                    },
                    {
                        "name": "Coming of Age",
                        "desc": "You touch one humanoid who is a young adult. For the next 24 hours, whenever the target makes an ability check, it may roll a d4 and add the number rolled to the ability check. A creature can benefit from this rite only once."
                    },
                    {
                        "name": "Dedication",
                        "desc": "You touch one humanoid who wishes to be dedicated to your god's service. For the next 24 hours, whenever the target makes a saving throw, it may roll a d4 and add the number rolled to the save. A creature can benefit from this rite only once."
                    },
                    {
                        "name": "Funeral Rite",
                        "desc": "You touch one corpse, and for the next 7 days, the target cannot become undead by any means short of a Wish spell."
                    },
                    {
                        "name": "Wedding",
                        "desc": "You touch adult humanoids willing to be bonded together in marriage. For the next 7 days, each target gains a +2 bonus to AC while they are within 30ft. of each other. A creature can benefit from this rite again only if widowed."
                    }
                ]
            }
        ],
        "levels": null,
        
        "lists": ["cleric", "paladin"],
        "source": "Xanathar's Guide to Everything"
    },
    "hail-of-thorns": {
        "name": "Hail of Thorns",
        "level": 1,
        "school": "conjuration",

        "castTime": {
            "amount": 1,
            "time": "bonus action"
        },
        "range": "self",
        "vsm": [true, false, false],
        "duration": {
            "amount": 1,
            "time": "minute",
            "concentration": true
        },
        
        "desc": [
            {
                "desc": "The next time you hit a creature with a ranged weapon attack before the spell ends, this spell creates a rain of thorns that sprouts from your ranged weapon or ammunition. In addition to the normal effect of the attack, the target of the attack and each creature within 5ft. of it must make a DEX saving throw. A creature takes {*}d10 piercing damage on a failed save, or half as much damage on a successful one."
            }
        ],
        "levels": [1, 2, 3, 4, 5, 6, 6, 6, 6],
        
        "lists": ["ranger"],
        "source": "Player's Handbook"
    },
    "mage-armor": {
        "name": "Mage Armor",
        "level": 1,
        "school": "abjuration",

        "castTime": {
            "amount": 1,
            "time": "action"
        },
        "range": "touch",
        "vsm": [true, true, "a piece of cured leather"],
        "duration": {
            "amount": 8,
            "time": "hour"
        },
        
        "desc": [
            {
                "desc": "You touch a willing creature who is not wearing armor, and a protective magical force surrounds it until the spell ends. The target's base AC becomes 13 + its DEX modifier. The spell ends if the target dons armor or if you dismiss the spell as an action."
            }
        ],
        "levels": null,
        
        "lists": ["sorcerer", "wizard"],
        "source": "Player's Handbook"
    },
    "shield": {
        "name": "Shield",
        "level": 1,
        "school": "abjuration",

        "castTime": {
            "amount": 1,
            "time": "reaction",
            "condition": "you are hit by an attack or targeted by the magic missile spell"
        },
        "range": "self",
        "vsm": [true, true, false],
        "duration": {
            "amount": 1,
            "time": "round"
        },
        
        "desc": [
            {
                "desc": "An invisible barrier of magical force appears and protects you. Until the start of your next turn, you have a +5 bonus to AC, including against the triggering attack, and you take no damage from magic missile."
            }
        ],
        "levels": null,
        
        "lists": ["sorcerer", "wizard"],
        "source": "Player's Handbook"
    },
    "silvery-barbs": {
        "name": "Silvery Barbs",
        "level": 1,
        "school": "enchantment",

        "castTime": {
            "amount": 1,
            "time": "reaction",
            "condition": "a creature you can see within 60ft. succeeds on an attack roll, an ability check, or a saving throw"
        },
        "range": "60ft.",
        "vsm": [true, false, false],
        "duration": {
            "time": "instantaneous"
        },
        
        "desc": [
            {
                "desc": "You magically distract the triggering creature and turn its momentary uncertainty into encouragement for another creature. The triggering creature must reroll the d20 and use the lower roll. You may then also choose a different creature you can see within range (you can choose yourself). The chosen creature has advantage on the next attack roll, ability check, or saving throw it makes within 1 minute. A creature can be empowered by only one use of this spell at a time."
            }
        ],
        "levels": null,
        
        "lists": ["bard", "sorcerer", "wizard"],
        "source": "Strixhaven: A Curriculum of Chaos"
    }
}